wagtail_marketing/__init__.py
wagtail_marketing/apps.py
wagtail_marketing/conf.py
wagtail_marketing/helpers.py
wagtail_marketing/wagtail_hooks.py
wagtail_marketing/locale/en/LC_MESSAGES/django.mo
wagtail_marketing/locale/en/LC_MESSAGES/django.po
wagtail_marketing/locale/nl/LC_MESSAGES/django.mo
wagtail_marketing/locale/nl/LC_MESSAGES/django.po
wagtail_marketing/locale/nl_BE/LC_MESSAGES/django.mo
wagtail_marketing/locale/nl_BE/LC_MESSAGES/django.po
wagtail_marketing/locale/nl_NL/LC_MESSAGES/django.mo
wagtail_marketing/locale/nl_NL/LC_MESSAGES/django.po
wagtail_marketing_addons-0.9.dist-info/LICENSE
wagtail_marketing_addons-0.9.dist-info/METADATA
wagtail_marketing_addons-0.9.dist-info/WHEEL
wagtail_marketing_addons-0.9.dist-info/top_level.txt
wagtail_marketing_addons-0.9.dist-info/RECORD
