Metadata-Version: 2.1
Name: wagtail-marketing-addons
Version: 0.9
Summary: A Wagtail add-on for supporting marketeer's in daily activities
Home-page: https://www.lukkien.com/
Author: Lukkien BV
Author-email: support@lukkien.com
License: BSD
Classifier: Development Status :: 5 - Production/Stable
Classifier: Environment :: Web Environment
Classifier: Intended Audience :: Developers
Classifier: License :: OSI Approved :: BSD License
Classifier: Operating System :: OS Independent
Classifier: Programming Language :: Python
Classifier: Programming Language :: Python :: 3
Classifier: Programming Language :: Python :: 3.8
Classifier: Programming Language :: Python :: 3.9
Classifier: Programming Language :: Python :: 3.10
Classifier: Framework :: Django
Classifier: Framework :: Wagtail
Classifier: Framework :: Wagtail :: 5
Classifier: Framework :: Wagtail :: 6
Classifier: Topic :: Internet :: WWW/HTTP :: Site Management
License-File: LICENSE
Requires-Dist: wagtail-modeladmin>2.0.0
Provides-Extra: doc
Requires-Dist: mkdocs; extra == "doc"
Requires-Dist: pymdown-extensions; extra == "doc"
Provides-Extra: test
Requires-Dist: pytest; extra == "test"
Requires-Dist: pytest-cov; extra == "test"
Requires-Dist: pytest-django; extra == "test"
Requires-Dist: pytest-pythonpath; extra == "test"
Requires-Dist: coverage; extra == "test"
Requires-Dist: factory-boy; extra == "test"
Requires-Dist: psycopg==3.1.18; extra == "test"
Requires-Dist: tox; extra == "test"
Requires-Dist: flake8; extra == "test"
Requires-Dist: isort; extra == "test"
